LICENSE.txt
README.md
setup.py
qiaotest2022/__init__.py
qiaotest2022/example.py
qiaotest2022.egg-info/PKG-INFO
qiaotest2022.egg-info/SOURCES.txt
qiaotest2022.egg-info/dependency_links.txt
qiaotest2022.egg-info/top_level.txt