Metadata-Version: 2.1
Name: qiaotest2022
Version: 1.0.0
Summary: 测试本地发布模块
Author: dgwqqqqq
Author-email: aaaa@qq.com
License-File: LICENSE.txt
